README.rst
setup.cfg
setup.py
xmlmanip.py
xmlmanip.egg-info/PKG-INFO
xmlmanip.egg-info/SOURCES.txt
xmlmanip.egg-info/dependency_links.txt
xmlmanip.egg-info/requires.txt
xmlmanip.egg-info/top_level.txt