Metadata-Version: 1.2
Name: xmlmanip
Version: 1.1.5.dev0
Summary: Convert XML documents to dict and easily search for and retrieve the data they contain.
Home-page: https://github.com/jjorissen52/xmlmanip
Author: John-Paul Jorissen
Author-email: jjorissen52@gmail.com
License: Apache
Keywords: XML document parse search
Platform: UNKNOWN
Classifier: Development Status :: 3 - Alpha
Classifier: Intended Audience :: Developers
Classifier: Programming Language :: Python :: 3.6
Classifier: Operating System :: Microsoft :: Windows :: Windows 10
Classifier: Operating System :: POSIX :: Linux
Classifier: License :: OSI Approved :: Apache Software License
Classifier: Programming Language :: Python :: 3.6
Requires-Python: >=3.6
